LICENSE
MANIFEST.in
README.md
setup.cfg
setup.py
problemo/__init__.py
problemo/solverwrap.py
problemo.egg-info/PKG-INFO
problemo.egg-info/SOURCES.txt
problemo.egg-info/dependency_links.txt
problemo.egg-info/pbr.json
problemo.egg-info/requires.txt
problemo.egg-info/top_level.txt